pynecore/__init__.py
pynecore/cli/__init__.py
pynecore/cli/app.py
pynecore/cli/commands/__init__.py
pynecore/cli/commands/benchmark.py
pynecore/cli/commands/compile.py
pynecore/cli/commands/data.py
pynecore/cli/commands/run.py
pynecore/cli/utils/__init__.py
pynecore/cli/utils/api_error_handler.py
pynecore/cli/utils/error_hook.py
pynecore/core/__init__.py
pynecore/core/callable_module.py
pynecore/core/class_property.py
pynecore/core/csv_file.py
pynecore/core/data_converter.py
pynecore/core/datetime.py
pynecore/core/function_isolation.py
pynecore/core/import_hook.py
pynecore/core/module_property.py
pynecore/core/ohlcv_file.py
pynecore/core/overload.py
pynecore/core/pine_cast.py
pynecore/core/pine_export.py
pynecore/core/pine_method.py
pynecore/core/pine_range.py
pynecore/core/pine_udt.py
pynecore/core/random.py
pynecore/core/resampler.py
pynecore/core/safe_convert.py
pynecore/core/script.py
pynecore/core/script_runner.py
pynecore/core/series.py
pynecore/core/strategy_stats.py
pynecore/core/syminfo.py
pynecore/lib/__init__.py
pynecore/lib/adjustment.py
pynecore/lib/alert.py
pynecore/lib/alert.pyi
pynecore/lib/array.py
pynecore/lib/barmerge.py
pynecore/lib/barstate.py
pynecore/lib/box.py
pynecore/lib/chart.py
pynecore/lib/color.py
pynecore/lib/currency.py
pynecore/lib/dayofweek.py
pynecore/lib/display.py
pynecore/lib/dividends.py
pynecore/lib/earnings.py
pynecore/lib/extend.py
pynecore/lib/font.py
pynecore/lib/format.py
pynecore/lib/hline.py
pynecore/lib/hline.pyi
pynecore/lib/label.py
pynecore/lib/line.py
pynecore/lib/linefill.py
pynecore/lib/location.py
pynecore/lib/log.py
pynecore/lib/map.py
pynecore/lib/math.py
pynecore/lib/matrix.py
pynecore/lib/order.py
pynecore/lib/plot.py
pynecore/lib/plot.pyi
pynecore/lib/polyline.py
pynecore/lib/position.py
pynecore/lib/runtime.py
pynecore/lib/scale.py
pynecore/lib/session.py
pynecore/lib/shape.py
pynecore/lib/size.py
pynecore/lib/string.py
pynecore/lib/syminfo.py
pynecore/lib/ta.py
pynecore/lib/table.py
pynecore/lib/text.py
pynesys_pynecore-6.3.4.dist-info/licenses/LICENSE.txt
pynesys_pynecore-6.3.4.dist-info/METADATA
pynesys_pynecore-6.3.4.dist-info/WHEEL
pynesys_pynecore-6.3.4.dist-info/entry_points.txt
pynesys_pynecore-6.3.4.dist-info/top_level.txt
pynesys_pynecore-6.3.4.dist-info/RECORD
